flyconf/__init__.py
flyconf/__main__.py
flyconf/lexer.py
flyconf/model.py
flyconf/parser.py
flyconf/transformer.py
flyconf-1.0.2.dist-info/METADATA
flyconf-1.0.2.dist-info/WHEEL
flyconf-1.0.2.dist-info/entry_points.txt
flyconf-1.0.2.dist-info/top_level.txt
flyconf-1.0.2.dist-info/RECORD
