Metadata-Version: 2.4
Name: flyconf
Version: 1.0.2
Summary: A parser for fc configuration files with support for complex structures, variables, and environment-aware configurations
Author: zhum
License: MIT
Requires-Python: >=3.8
Provides-Extra: dev
Requires-Dist: pytest>=7.0; extra == "dev"
Requires-Dist: pytest-cov>=4.0; extra == "dev"
